comlink/__init__.py
comlink/consumer.py
comlink/events.py
comlink/queue.py
comlink-0.3.1.dist-info/LICENSE
comlink-0.3.1.dist-info/WHEEL
comlink-0.3.1.dist-info/METADATA
comlink-0.3.1.dist-info/RECORD
