Metadata-Version: 2.1
Name: comlink
Version: 0.3.1
Summary: Send and receive messages by using SQS queues.
Home-page: https://github.com/art1415926535/comlink
License: MIT
Author: Artem Fedotov
Requires-Python: >=3.10,<4.0
Classifier: License :: OSI Approved :: MIT License
Classifier: Programming Language :: Python :: 3
Classifier: Programming Language :: Python :: 3.10
Requires-Dist: aiobotocore (>=2,<3)
Project-URL: Bug Tracker, https://github.com/art1415926535/comlink/issues
Project-URL: Change Log, https://github.com/art1415926535/comlink/releases
Project-URL: Repository, https://github.com/art1415926535/comlink
